{
  "slug": "blank",
  "name": "Blank",
  "videoId": "w8uvvvRi6kQ",
  "blogUrl": "https://deafened.org/asl-sign-blank/",
  "semanticField": "Attribute",
  "lexicalClass": "Adjective",
  "difficulty": 3,
  "signType": "SymmetricalOrAlternating",
  "frequency": 2.429,
  "frequencyLabel": "Uncommon",
  "hasLexData": true,
  "handshape": "open_8",
  "selectedFingers": "m",
  "flexion": "Flat",
  "flexionChange": "0",
  "spread": "NA",
  "movement": "Straight",
  "repeatedMovement": "0",
  "majorLocation": "Neutral",
  "minorLocation": "Neutral",
  "secondMinorLocation": "Neutral",
  "contact": "1",
  "nonDominantHandshape": "open_8",
  "ulnarRotation": "0",
  "thumbPosition": "Open",
  "thumbContact": "0",
  "iconicity": 2.304,
  "iconicityLabel": "Arbitrary",
  "iconicityType": "Arbitrary",
  "isCompound": false,
  "numMorphemes": 1,
  "ageOfAcquisition": null,
  "aoaLabel": null,
  "neighborhoodDensity": 5,
  "signBankTranslations": "bare, blank, clear, depleted, empty",
  "signBankId": "796"
}