{
  "slug": "cancel",
  "name": "Cancel",
  "videoId": "rP6ckIwyG5Y",
  "blogUrl": "https://deafened.org/asl-sign-cancel/",
  "semanticField": "Event",
  "lexicalClass": "Verb",
  "difficulty": 1,
  "signType": "AsymmetricalDifferentHandshape",
  "frequency": 5.333,
  "frequencyLabel": "Common",
  "hasLexData": true,
  "handshape": "1",
  "selectedFingers": "i",
  "flexion": "FullyOpen",
  "flexionChange": "0",
  "spread": "NA",
  "movement": "X-Shaped",
  "repeatedMovement": "0",
  "majorLocation": "Hand",
  "minorLocation": "Palm",
  "secondMinorLocation": "HandAway",
  "contact": "1",
  "nonDominantHandshape": "B",
  "ulnarRotation": "1",
  "thumbPosition": "Closed",
  "thumbContact": "0",
  "iconicity": 4.281,
  "iconicityLabel": "Moderately Iconic",
  "iconicityType": "NA",
  "isCompound": false,
  "numMorphemes": 1,
  "ageOfAcquisition": null,
  "aoaLabel": null,
  "neighborhoodDensity": 3,
  "signBankTranslations": "cancel, correct, critical, criticize, critique, discriminate, discrimination, grade",
  "signBankId": "1167"
}