{
  "slug": "curtsey",
  "name": "Curtsey",
  "videoId": "Rls-xT0Z9Nc",
  "blogUrl": "https://deafened.org/asl-sign-curtsey/",
  "semanticField": null,
  "lexicalClass": "Verb",
  "difficulty": 2,
  "signType": "AsymmetricalDifferentHandshape",
  "frequency": 3.667,
  "frequencyLabel": "Moderate",
  "hasLexData": true,
  "handshape": "v",
  "selectedFingers": "im",
  "flexion": "FullyOpen",
  "flexionChange": "1",
  "spread": "1",
  "movement": "None",
  "repeatedMovement": "0",
  "majorLocation": "Hand",
  "minorLocation": "Palm",
  "secondMinorLocation": "NA",
  "contact": "1",
  "nonDominantHandshape": "B",
  "ulnarRotation": "0",
  "thumbPosition": "Closed",
  "thumbContact": "0",
  "iconicity": 4.04,
  "iconicityLabel": "Moderately Iconic",
  "iconicityType": null,
  "isCompound": false,
  "numMorphemes": 1,
  "ageOfAcquisition": null,
  "aoaLabel": null,
  "neighborhoodDensity": 2,
  "signBankTranslations": null,
  "signBankId": null
}