{
  "slug": "firetruck",
  "name": "Firetruck",
  "videoId": "Wnx0f3Q8VGA",
  "blogUrl": "https://deafened.org/asl-sign-firetruck/",
  "semanticField": null,
  "lexicalClass": "Noun",
  "difficulty": 3,
  "signType": "One-Handed",
  "frequency": 2.222,
  "frequencyLabel": "Uncommon",
  "hasLexData": true,
  "handshape": "4",
  "selectedFingers": "imrp",
  "flexion": "FullyOpen",
  "flexionChange": "0",
  "spread": "1",
  "movement": "Straight",
  "repeatedMovement": "0",
  "majorLocation": "Head",
  "minorLocation": "Forehead",
  "secondMinorLocation": "NA",
  "contact": "1",
  "nonDominantHandshape": "NA",
  "ulnarRotation": "0",
  "thumbPosition": "Closed",
  "thumbContact": "0",
  "iconicity": 1.903,
  "iconicityLabel": "Arbitrary",
  "iconicityType": "Arbitrary",
  "isCompound": true,
  "numMorphemes": 2,
  "ageOfAcquisition": null,
  "aoaLabel": null,
  "neighborhoodDensity": 7,
  "signBankTranslations": null,
  "signBankId": null
}