{
  "slug": "gold",
  "name": "Gold",
  "videoId": "7B12zWKuJus",
  "blogUrl": "https://deafened.org/asl-sign-gold/",
  "semanticField": "Color",
  "lexicalClass": "Noun",
  "difficulty": 2,
  "signType": "One-Handed",
  "frequency": 3.231,
  "frequencyLabel": "Moderate",
  "hasLexData": true,
  "handshape": "ily",
  "selectedFingers": "ip",
  "flexion": "FullyOpen",
  "flexionChange": "0",
  "spread": "NA",
  "movement": "None",
  "repeatedMovement": "0",
  "majorLocation": "Head",
  "minorLocation": "CheekNose",
  "secondMinorLocation": "NA",
  "contact": "1",
  "nonDominantHandshape": "NA",
  "ulnarRotation": "0",
  "thumbPosition": "Open",
  "thumbContact": "0",
  "iconicity": 1.032,
  "iconicityLabel": "Arbitrary",
  "iconicityType": "Arbitrary",
  "isCompound": true,
  "numMorphemes": 2,
  "ageOfAcquisition": null,
  "aoaLabel": null,
  "neighborhoodDensity": 3,
  "signBankTranslations": "color, gold",
  "signBankId": "2929"
}