{
  "slug": "high",
  "name": "High",
  "videoId": "OonF29RFfSI",
  "blogUrl": "https://deafened.org/asl-sign-high/",
  "semanticField": "Attribute",
  "lexicalClass": "Adjective",
  "difficulty": 2,
  "signType": "One-Handed",
  "frequency": 4.4,
  "frequencyLabel": "Moderate",
  "hasLexData": true,
  "handshape": "h",
  "selectedFingers": "im",
  "flexion": "FullyOpen",
  "flexionChange": "0",
  "spread": "0",
  "movement": "Curved",
  "repeatedMovement": "0",
  "majorLocation": "Neutral",
  "minorLocation": "Neutral",
  "secondMinorLocation": "Neutral",
  "contact": "0",
  "nonDominantHandshape": "NA",
  "ulnarRotation": "0",
  "thumbPosition": "Closed",
  "thumbContact": "0",
  "iconicity": 3.731,
  "iconicityLabel": "Moderately Iconic",
  "iconicityType": "Arbitrary",
  "isCompound": false,
  "numMorphemes": 1,
  "ageOfAcquisition": 52,
  "aoaLabel": "School Age (4-6 years)",
  "neighborhoodDensity": 4,
  "signBankTranslations": "high",
  "signBankId": "1767"
}