{
  "slug": "juggler",
  "name": "Juggler",
  "videoId": "mLODYR9QvZU",
  "blogUrl": "https://deafened.org/asl-sign-juggler/",
  "semanticField": "Event",
  "lexicalClass": "Noun",
  "difficulty": 3,
  "signType": "SymmetricalOrAlternating",
  "frequency": 2.867,
  "frequencyLabel": "Uncommon",
  "hasLexData": true,
  "handshape": "s",
  "selectedFingers": "imrp",
  "flexion": "FullyClosed",
  "flexionChange": "1",
  "spread": "NA",
  "movement": "Circular",
  "repeatedMovement": "1",
  "majorLocation": "Neutral",
  "minorLocation": "Neutral",
  "secondMinorLocation": "Neutral",
  "contact": "0",
  "nonDominantHandshape": "s",
  "ulnarRotation": "0",
  "thumbPosition": "Closed",
  "thumbContact": "1",
  "iconicity": 6.8,
  "iconicityLabel": "Highly Iconic",
  "iconicityType": "NA",
  "isCompound": false,
  "numMorphemes": 1,
  "ageOfAcquisition": null,
  "aoaLabel": null,
  "neighborhoodDensity": 4,
  "signBankTranslations": "balls, juggle, juggling, throw",
  "signBankId": "2985"
}