{
  "slug": "lucky",
  "name": "Lucky",
  "videoId": "Rxxt4x_DLjQ",
  "blogUrl": "https://deafened.org/asl-sign-lucky/",
  "semanticField": "Attribute",
  "lexicalClass": "Adjective",
  "difficulty": 2,
  "signType": "One-Handed",
  "frequency": 4.704,
  "frequencyLabel": "Common",
  "hasLexData": true,
  "handshape": "open_8",
  "selectedFingers": "m",
  "flexion": "Curved",
  "flexionChange": "0",
  "spread": "NA",
  "movement": "Straight",
  "repeatedMovement": "0",
  "majorLocation": "Head",
  "minorLocation": "Chin",
  "secondMinorLocation": "HeadAway",
  "contact": "1",
  "nonDominantHandshape": "NA",
  "ulnarRotation": "1",
  "thumbPosition": "Open",
  "thumbContact": "0",
  "iconicity": 1.29,
  "iconicityLabel": "Arbitrary",
  "iconicityType": "Arbitrary",
  "isCompound": false,
  "numMorphemes": 1,
  "ageOfAcquisition": null,
  "aoaLabel": null,
  "neighborhoodDensity": 0,
  "signBankTranslations": "fortunate, fortune, good luck, luck, luckily, lucky",
  "signBankId": "1632"
}