{
  "slug": "sarcastic",
  "name": "Sarcastic",
  "videoId": "rgqQGuAtsXw",
  "blogUrl": "https://deafened.org/asl-sign-sarcastic/",
  "semanticField": null,
  "lexicalClass": "Adjective",
  "difficulty": 2,
  "signType": "SymmetricalOrAlternating",
  "frequency": 4.571,
  "frequencyLabel": "Common",
  "hasLexData": true,
  "handshape": "flat_horns",
  "selectedFingers": "ip",
  "flexion": "Flat",
  "flexionChange": "0",
  "spread": "NA",
  "movement": "Back and Forth",
  "repeatedMovement": "0",
  "majorLocation": "Neutral",
  "minorLocation": "Neutral",
  "secondMinorLocation": "Neutral",
  "contact": "1",
  "nonDominantHandshape": "flat_horns",
  "ulnarRotation": "0",
  "thumbPosition": "Closed",
  "thumbContact": "0",
  "iconicity": 1.769,
  "iconicityLabel": "Arbitrary",
  "iconicityType": "Arbitrary",
  "isCompound": false,
  "numMorphemes": 1,
  "ageOfAcquisition": null,
  "aoaLabel": null,
  "neighborhoodDensity": 0,
  "signBankTranslations": null,
  "signBankId": null
}