{
  "slug": "sink",
  "name": "Sink",
  "videoId": "M03PAL-pL3w",
  "blogUrl": "https://deafened.org/asl-sign-sink/",
  "semanticField": null,
  "lexicalClass": "Verb",
  "difficulty": 3,
  "signType": "AsymmetricalDifferentHandshape",
  "frequency": 2.406,
  "frequencyLabel": "Uncommon",
  "hasLexData": true,
  "handshape": "3",
  "selectedFingers": "im",
  "flexion": "FullyOpen",
  "flexionChange": "0",
  "spread": "1",
  "movement": "Straight",
  "repeatedMovement": "0",
  "majorLocation": "Hand",
  "minorLocation": "Palm",
  "secondMinorLocation": "HandAway",
  "contact": "1",
  "nonDominantHandshape": "B",
  "ulnarRotation": "0",
  "thumbPosition": "Open",
  "thumbContact": "0",
  "iconicity": 3.467,
  "iconicityLabel": "Moderately Iconic",
  "iconicityType": "Arbitrary",
  "isCompound": false,
  "numMorphemes": 1,
  "ageOfAcquisition": null,
  "aoaLabel": null,
  "neighborhoodDensity": 6,
  "signBankTranslations": null,
  "signBankId": null
}