{
  "slug": "still",
  "name": "Still",
  "videoId": "F47q9ZFdtjo",
  "blogUrl": "https://deafened.org/asl-sign-still/",
  "semanticField": null,
  "lexicalClass": "Adverb",
  "difficulty": 1,
  "signType": "SymmetricalOrAlternating",
  "frequency": 5.667,
  "frequencyLabel": "Common",
  "hasLexData": true,
  "handshape": "y",
  "selectedFingers": "p",
  "flexion": "FullyOpen",
  "flexionChange": "0",
  "spread": "NA",
  "movement": "Curved",
  "repeatedMovement": "0",
  "majorLocation": "Neutral",
  "minorLocation": "Neutral",
  "secondMinorLocation": "Neutral",
  "contact": "0",
  "nonDominantHandshape": "y",
  "ulnarRotation": "1",
  "thumbPosition": "Open",
  "thumbContact": "0",
  "iconicity": 2.067,
  "iconicityLabel": "Arbitrary",
  "iconicityType": "Arbitrary",
  "isCompound": false,
  "numMorphemes": 1,
  "ageOfAcquisition": null,
  "aoaLabel": null,
  "neighborhoodDensity": 1,
  "signBankTranslations": "continue, enduring, even now, persist, persisting, still",
  "signBankId": "1118"
}