{
  "slug": "strawberry",
  "name": "Strawberry",
  "videoId": "epJQI7IZsoI",
  "blogUrl": "https://deafened.org/asl-sign-strawberry/",
  "semanticField": "Food",
  "lexicalClass": "Noun",
  "difficulty": 1,
  "signType": "One-Handed",
  "frequency": 5.667,
  "frequencyLabel": "Common",
  "hasLexData": true,
  "handshape": "f",
  "selectedFingers": "i",
  "flexion": "Curved",
  "flexionChange": "0",
  "spread": "NA",
  "movement": "Curved",
  "repeatedMovement": "1",
  "majorLocation": "Head",
  "minorLocation": "Mouth",
  "secondMinorLocation": "HeadAway",
  "contact": "1",
  "nonDominantHandshape": "NA",
  "ulnarRotation": "1",
  "thumbPosition": "Open",
  "thumbContact": "1",
  "iconicity": 1.292,
  "iconicityLabel": "Arbitrary",
  "iconicityType": null,
  "isCompound": false,
  "numMorphemes": 1,
  "ageOfAcquisition": null,
  "aoaLabel": null,
  "neighborhoodDensity": 2,
  "signBankTranslations": "food, fruit, grapes (CT sign), strawberry",
  "signBankId": "2020"
}