{
  "slug": "tired",
  "name": "Tired",
  "videoId": "LIw087ca2TM",
  "blogUrl": "https://deafened.org/asl-sign-tired/",
  "semanticField": "Attribute",
  "lexicalClass": "Adjective",
  "difficulty": 1,
  "signType": "SymmetricalOrAlternating",
  "frequency": 6.538,
  "frequencyLabel": "Very Common",
  "hasLexData": true,
  "handshape": "c",
  "selectedFingers": "imrp",
  "flexion": "Curved",
  "flexionChange": "0",
  "spread": "0",
  "movement": "Curved",
  "repeatedMovement": "0",
  "majorLocation": "Body",
  "minorLocation": "Clavicle",
  "secondMinorLocation": "NA",
  "contact": "1",
  "nonDominantHandshape": "c",
  "ulnarRotation": "0",
  "thumbPosition": "Open",
  "thumbContact": "0",
  "iconicity": 3.806,
  "iconicityLabel": "Moderately Iconic",
  "iconicityType": "Arbitrary",
  "isCompound": false,
  "numMorphemes": 1,
  "ageOfAcquisition": 30,
  "aoaLabel": "Toddler (2-3 years)",
  "neighborhoodDensity": 3,
  "signBankTranslations": "exhausted, tire, tired, worn out",
  "signBankId": "297"
}