{
  "slug": "topic",
  "name": "Topic",
  "videoId": "9cT84SbQl50",
  "blogUrl": "https://deafened.org/asl-sign-topic/",
  "semanticField": null,
  "lexicalClass": "Noun",
  "difficulty": 2,
  "signType": "SymmetricalOrAlternating",
  "frequency": 4.786,
  "frequencyLabel": "Common",
  "hasLexData": true,
  "handshape": "bent_v",
  "selectedFingers": "im",
  "flexion": "Bent",
  "flexionChange": "0",
  "spread": "1",
  "movement": "Curved",
  "repeatedMovement": "1",
  "majorLocation": "Neutral",
  "minorLocation": "Neutral",
  "secondMinorLocation": "NA",
  "contact": "0",
  "nonDominantHandshape": "bent_v",
  "ulnarRotation": "0",
  "thumbPosition": "Closed",
  "thumbContact": "0",
  "iconicity": 2.8,
  "iconicityLabel": "Arbitrary",
  "iconicityType": "Arbitrary",
  "isCompound": false,
  "numMorphemes": 1,
  "ageOfAcquisition": null,
  "aoaLabel": null,
  "neighborhoodDensity": 3,
  "signBankTranslations": "in other words, issue, paraphrase, phrase, quote, title, topic",
  "signBankId": "564"
}